Metadata-Version: 1.0
Name: start-cli
Version: 0.0.1
Summary: scaffold for quick start project
Home-page: https://github.com/istommao/start-cli
Author: codingcat
Author-email: istommao@gmail.com
License: UNKNOWN
Keywords: scaffold
Platform: UNKNOWN
